{"words": 1990, "paragraph": 49, "reference_counter": 13, "reference_years": [2006, 2009, 2012, 2003, 2013, 2013, 2010, 2012, 2003, 2009, 2008, 2006], "publish_year": 2014, "out_of_date": [8, 5, 2, 11, 1, 1, 4, 2, 11, 5, 6, 8], "similar_paper": [{"name": "基于词向量与句法树的中文句子情感分析_相若晨", "sim": 0.5018858909606934}, {"name": "基于卷积神经网络的微博情感倾向性分析_刘龙飞", "sim": 0.44736286997795105}, {"name": "基于POS_CBOW语言模型的相似词分析_阮冬茹", "sim": 0.364590048789978}, {"name": "微博文本的句向量表示及相似度计算方法研究_段旭磊", "sim": 0.36438876390457153}, {"name": "基于Word2Vec的一种文档向量表示_唐明", "sim": 0.3492637276649475}, {"name": "基于词向量的微博事件追踪方法_张佳明", "sim": 0.34751200675964355}, {"name": "Word2vec的工作原理及应用探究_周练", "sim": 0.3410142660140991}, {"name": "基于词向量语义分类的微博实体链接方法_冯冲", "sim": 0.3405884802341461}, {"name": "基于词向量的中文词汇蕴涵关系识别_张志昌", "sim": 0.3376619219779968}, {"name": "基于表示学习的中文分词_刘春丽", "sim": 0.3311147689819336}]}