{"words": 6859, "paragraph": 57, "reference_counter": 1, "reference_years": [], "publish_year": 0, "out_of_date": [], "author_institutions": ["中国人民大学"], "first_author": "李志宇", "authors": ["李志宇", "梁循", "周小平"], "journal": "中文信息学报", "fund_project": ["国家自然科学基金"], "references_source": [], "similar_paper": [{"name": "基于词向量与句法树的中文句子情感分析_相若晨", "sim": 43.54577660560608}, {"name": "基于语义关系约束和词语关系信息的句向量研究_作者", "sim": 41.68967306613922}, {"name": "利用word2vec对中文词进行聚类的研究_郑文超", "sim": 40.49328565597534}, {"name": "基于词向量的情感新词发现方法_杨阳", "sim": 39.1541987657547}, {"name": "基于知网义原词向量表示的无监督词义消歧方法_唐共波", "sim": 38.611626625061035}, {"name": "基于词向量的句子相似度计算及其应用研究_郭胜国", "sim": 37.51417398452759}, {"name": "基于卷积神经网络的微博情感倾向性分析_刘龙飞", "sim": 36.324018239974976}, {"name": "基于Word2Vec的一种文档向量表示_唐明", "sim": 35.86512804031372}, {"name": "蕴含地理事件微博客消息的自动识别方法_仇培元", "sim": 35.59008836746216}, {"name": "融合Word2vec与TextRank的关键词抽取研究_宁建飞", "sim": 35.217270255088806}], "authors_pro": 1.22449, "first_author_pro": 0.90909, "author_institutions_pro": 0.60606, "journal_pro": 4.12371, "fund_project_pro": 38.83495, "references_source_pro": 0, "out_of_date_pro": 0, "most_similar": 43.54577660560608, "sims_pro": 38.40052396059036}